wg_gesucht/__init__.py
wg_gesucht/_version.py
wg_gesucht/cli.py
wg_gesucht/crawler.py
wg_gesucht/create_results_folders.py
wg_gesucht/logger.py
wg_gesucht/user_details.py
wg_gesucht_crawler_cli-0.1.9.dist-info/AUTHORS.rst
wg_gesucht_crawler_cli-0.1.9.dist-info/LICENSE
wg_gesucht_crawler_cli-0.1.9.dist-info/METADATA
wg_gesucht_crawler_cli-0.1.9.dist-info/WHEEL
wg_gesucht_crawler_cli-0.1.9.dist-info/entry_points.txt
wg_gesucht_crawler_cli-0.1.9.dist-info/top_level.txt
wg_gesucht_crawler_cli-0.1.9.dist-info/RECORD
