Metadata-Version: 2.1
Name: wg-gesucht-crawler-cli
Version: 0.1.9
Summary: Python web crawler / scraper for WG-Gesucht. Crawls the WG-Gesucht site for new apartment listings and send a message to the poster, based off your saved filters and saved text template.
Home-page: https://github.com/grantwilliams/wg-gesucht-crawler-cli
Author: Grant Williams
Author-email: grant.williams2986@gmail.com
License: MIT
Platform: UNKNOWN
Classifier: Development Status :: 5 - Production/Stable
Classifier: Environment :: Console
Classifier: Intended Audience :: Developers
Classifier: License :: OSI Approved :: MIT License
Classifier: Natural Language :: English
Classifier: Operating System :: OS Independent
Classifier: Programming Language :: Python :: 3
Classifier: Programming Language :: Python :: 3.3
Classifier: Programming Language :: Python :: 3.4
Classifier: Programming Language :: Python :: 3.5
Classifier: Programming Language :: Python :: 3.6
Classifier: Programming Language :: Python :: 3 :: Only
Requires-Dist: beautifulsoup4 (==4.6.0)
Requires-Dist: certifi (==2018.4.16)
Requires-Dist: chardet (==3.0.4)
Requires-Dist: click (==6.7)
Requires-Dist: idna (==2.7)
Requires-Dist: requests (==2.21.0)
Requires-Dist: urllib3 (==1.23)
